MANIFEST.in
README.txt
setup.py
collective/__init__.py
collective.socialbar.egg-info/PKG-INFO
collective.socialbar.egg-info/SOURCES.txt
collective.socialbar.egg-info/dependency_links.txt
collective.socialbar.egg-info/entry_points.txt
collective.socialbar.egg-info/namespace_packages.txt
collective.socialbar.egg-info/not-zip-safe
collective.socialbar.egg-info/requires.txt
collective.socialbar.egg-info/top_level.txt
collective/socialbar/__init__.py
collective/socialbar/configure.zcml
collective/socialbar/interfaces.py
collective/socialbar/viewlet.pt
collective/socialbar/profiles/default/browserlayer.xml
collective/socialbar/profiles/default/metadata.xml
collective/socialbar/resources/facebook.png
collective/socialbar/resources/gplus.png
collective/socialbar/resources/twitter.png
docs/HISTORY.txt