Metadata-Version: 1.1
Name: collective.socialbar
Version: 1.1
Summary: socialbar viewlet
Home-page: http://svn.plone.org/svn/collective/
Author: Izhar Firdaus
Author-email: izhar@inigo-tech.com
License: GPL
Keywords: plone social viewlet zope
Platform: UNKNOWN
Classifier: Programming Language :: Python
